databricks/__init__.py
databricks/sql/__init__.py
databricks/sql/auth/__init__.py
databricks/sql/auth/auth.py
databricks/sql/auth/auth_utils.py
databricks/sql/auth/authenticators.py
databricks/sql/auth/common.py
databricks/sql/auth/endpoint.py
databricks/sql/auth/oauth.py
databricks/sql/auth/oauth_http_handler.py
databricks/sql/auth/retry.py
databricks/sql/auth/thrift_http_client.py
databricks/sql/auth/token_federation.py
databricks/sql/backend/databricks_client.py
databricks/sql/backend/sea/backend.py
databricks/sql/backend/sea/models/__init__.py
databricks/sql/backend/sea/models/base.py
databricks/sql/backend/sea/models/requests.py
databricks/sql/backend/sea/models/responses.py
databricks/sql/backend/sea/queue.py
databricks/sql/backend/sea/result_set.py
databricks/sql/backend/sea/utils/constants.py
databricks/sql/backend/sea/utils/conversion.py
databricks/sql/backend/sea/utils/filters.py
databricks/sql/backend/sea/utils/http_client.py
databricks/sql/backend/sea/utils/normalize.py
databricks/sql/backend/thrift_backend.py
databricks/sql/backend/types.py
databricks/sql/backend/utils/__init__.py
databricks/sql/backend/utils/guid_utils.py
databricks/sql/client.py
databricks/sql/cloudfetch/download_manager.py
databricks/sql/cloudfetch/downloader.py
databricks/sql/common/feature_flag.py
databricks/sql/common/http.py
databricks/sql/common/http_utils.py
databricks/sql/common/unified_http_client.py
databricks/sql/common/url_utils.py
databricks/sql/exc.py
databricks/sql/experimental/__init__.py
databricks/sql/experimental/oauth_persistence.py
databricks/sql/parameters/__init__.py
databricks/sql/parameters/native.py
databricks/sql/parameters/py.typed
databricks/sql/py.typed
databricks/sql/result_set.py
databricks/sql/session.py
databricks/sql/telemetry/circuit_breaker_manager.py
databricks/sql/telemetry/latency_logger.py
databricks/sql/telemetry/models/endpoint_models.py
databricks/sql/telemetry/models/enums.py
databricks/sql/telemetry/models/event.py
dt_databricks_sql_connector-4.2.4.dist-info/licenses/LICENSE
dt_databricks_sql_connector-4.2.4.dist-info/METADATA
dt_databricks_sql_connector-4.2.4.dist-info/WHEEL
dt_databricks_sql_connector-4.2.4.dist-info/RECORD
